design.sv
// 4-bit Up Counter

  module up_counter(
    input clk,
    input reset,
    input enable,
    output reg [3:0] count
  );

  always @(posedge clk) begin
    if (reset)				// If reset = 1
      count <= 4'b0000;		// count = 0, counter resets to 0 (or, in binary: 0000)
    else if (enable)
      count <= count + 1;
  end
  
endmodule

testbench.sv
// Testbench

module testbench;
  
reg clk;
reg reset;
reg enable;
wire [3:0] count;
  
// Instantiate the counter
up_counter uut (
  .clk(clk),
  .reset(reset),
  .enable(enable),
  .count(count)
);
  
// Clock generation
always #5 clk = ~clk;
  
initial begin
  $dumpfile("waveform.vcd");
  $dumpvars(0, testbench);
    
  // Initialise signals
  clk = 0;
  reset = 1;
  enable = 0;
    
  #10 reset = 0; enable = 1; // Start counting
  #100 enable = 0;		  // Stop counting
  #20 enable = 1;			  // Start again
  #50 reset = 1;			  // Reset
  #10 reset = 0; enable = 1;
    
  #50 $finish;
    
end
  
endmodule

waveform.vcd
$date
	Thu Jul 10 23:35:40 2025
$end
$version
	Icarus Verilog
$end
$timescale
	1s
$end
$scope module testbench $end
$var wire 4 ! count [3:0] $end
$var reg 1 " clk $end
$var reg 1 # enable $end
$var reg 1 $ reset $end
$scope module uut $end
$var wire 1 " clk $end
$var wire 1 # enable $end
$var wire 1 $ reset $end
$var reg 4 % count [3:0] $end
$upscope $end
$upscope $end
$enddefinitions $end
$comment Show the parameter values. $end
$dumpall
$end
#0
$dumpvars
bx %
1$
0#
0"
bx !
$end
#5
b0 !
b0 %
1"
#10
0"
1#
0$
#15
b1 !
b1 %
1"
#20
0"
#25
b10 !
b10 %
1"
#30
0"
#35
b11 !
b11 %
1"
#40
0"
#45
b100 !
b100 %
1"
#50
0"
#55
b101 !
b101 %
1"
#60
0"
#65
b110 !
b110 %
1"
#70
0"
#75
b111 !
b111 %
1"
#80
0"
#85
b1000 !
b1000 %
1"
#90
0"
#95
b1001 !
b1001 %
1"
#100
0"
#105
b1010 !
b1010 %
1"
#110
0"
0#
#115
1"
#120
0"
#125
1"
#130
0"
1#
#135
b1011 !
b1011 %
1"
#140
0"
#145
b1100 !
b1100 %
1"
#150
0"
#155
b1101 !
b1101 %
1"
#160
0"
#165
b1110 !
b1110 %
1"
#170
0"
#175
b1111 !
b1111 %
1"
#180
0"
1$
#185
b0 !
b0 %
1"
#190
0"
0$
#195
b1 !
b1 %
1"
#200
0"
#205
b10 !
b10 %
1"
#210
0"
#215
b11 !
b11 %
1"
#220
0"
#225
b100 !
b100 %
1"
#230
0"
#235
b101 !
b101 %
1"
